pokemb/__init__.py
pokemb/mod.py
pokemb/pred.py
pokemb/utils.py
pokemb/data/encodings.pkl
pokemb-0.1.2.dist-info/METADATA
pokemb-0.1.2.dist-info/WHEEL
pokemb-0.1.2.dist-info/top_level.txt
pokemb-0.1.2.dist-info/RECORD
